ipyvuetify/Html.py
ipyvuetify/Themes.py
ipyvuetify/VuetifyTemplate.py
ipyvuetify/__init__.py
ipyvuetify/_version.py
ipyvuetify/components.py
ipyvuetify/py.typed
ipyvuetify/extra/__init__.py
ipyvuetify/extra/file_input.py
ipyvuetify/extra/file_input.vue
ipyvuetify/generated/Alert.py
ipyvuetify/generated/App.py
ipyvuetify/generated/AppBar.py
ipyvuetify/generated/AppBarNavIcon.py
ipyvuetify/generated/Autocomplete.py
ipyvuetify/generated/Avatar.py
ipyvuetify/generated/Badge.py
ipyvuetify/generated/Banner.py
ipyvuetify/generated/BottomNavigation.py
ipyvuetify/generated/BottomSheet.py
ipyvuetify/generated/Breadcrumbs.py
ipyvuetify/generated/BreadcrumbsDivider.py
ipyvuetify/generated/BreadcrumbsItem.py
ipyvuetify/generated/Btn.py
ipyvuetify/generated/BtnToggle.py
ipyvuetify/generated/Calendar.py
ipyvuetify/generated/CalendarDaily.py
ipyvuetify/generated/CalendarMonthly.py
ipyvuetify/generated/CalendarWeekly.py
ipyvuetify/generated/Card.py
ipyvuetify/generated/CardActions.py
ipyvuetify/generated/CardSubtitle.py
ipyvuetify/generated/CardText.py
ipyvuetify/generated/CardTitle.py
ipyvuetify/generated/Carousel.py
ipyvuetify/generated/CarouselItem.py
ipyvuetify/generated/CarouselReverseTransition.py
ipyvuetify/generated/CarouselTransition.py
ipyvuetify/generated/Checkbox.py
ipyvuetify/generated/Chip.py
ipyvuetify/generated/ChipGroup.py
ipyvuetify/generated/Col.py
ipyvuetify/generated/ColorPicker.py
ipyvuetify/generated/ColorPickerCanvas.py
ipyvuetify/generated/ColorPickerSwatches.py
ipyvuetify/generated/Combobox.py
ipyvuetify/generated/Container.py
ipyvuetify/generated/Content.py
ipyvuetify/generated/Counter.py
ipyvuetify/generated/Data.py
ipyvuetify/generated/DataFooter.py
ipyvuetify/generated/DataIterator.py
ipyvuetify/generated/DataTable.py
ipyvuetify/generated/DataTableHeader.py
ipyvuetify/generated/DatePicker.py
ipyvuetify/generated/DatePickerDateTable.py
ipyvuetify/generated/DatePickerHeader.py
ipyvuetify/generated/DatePickerMonthTable.py
ipyvuetify-1.11.0.dist-info/LICENSE
ipyvuetify-1.11.0.dist-info/METADATA
ipyvuetify-1.11.0.dist-info/WHEEL
ipyvuetify-1.11.0.dist-info/top_level.txt
ipyvuetify-1.11.0.dist-info/RECORD
