Metadata-Version: 2.2
Name: ipyvuetify
Version: 1.11.0
Summary: Jupyter widgets based on vuetify UI components
Author-email: Mario Buikhuizen <mbuikhuizen@gmail.com>, Maarten Breddels <maartenbreddels@gmail.com>
License: MIT
Project-URL: repository, https://github.com/widgetti/ipyvuetify
Keywords: ipython,jupyter,widgets
Classifier: Development Status :: 5 - Production/Stable
Classifier: Framework :: IPython
Classifier: Intended Audience :: Developers
Classifier: Intended Audience :: Science/Research
Classifier: Topic :: Multimedia :: Graphics
Classifier: License :: OSI Approved :: MIT License
Classifier: Programming Language :: Python :: 3.6
Classifier: Programming Language :: Python :: 3.7
Classifier: Programming Language :: Python :: 3.8
Classifier: Programming Language :: Python :: 3.9
Classifier: Programming Language :: Python :: 3.10
Classifier: Programming Language :: Python :: 3.11
Requires-Python: >=3.6
License-File: LICENSE
Requires-Dist: ipyvue<2,>=1.7
Provides-Extra: dev
Requires-Dist: nox; extra == "dev"
Requires-Dist: pre-commit; extra == "dev"
Requires-Dist: mypy; extra == "dev"
Provides-Extra: test
Requires-Dist: pytest; extra == "test"
Requires-Dist: pytest-playwright<0.6; extra == "test"
Requires-Dist: nbformat<5.10; extra == "test"
Requires-Dist: jupyterlab<4; extra == "test"
Requires-Dist: solara[pytest]; extra == "test"
Provides-Extra: doc
Requires-Dist: sphinx<7; extra == "doc"
Requires-Dist: jupyter-sphinx; extra == "doc"
Requires-Dist: ipykernel; extra == "doc"
Requires-Dist: pydata-sphinx-theme; extra == "doc"
Requires-Dist: sphinx-design; extra == "doc"
Requires-Dist: sphinx_rtd_theme; extra == "doc"
